{
  "project_info": {
    "project_number": "1042387473888",
    "project_id": "fruits-hub-c571a",
    "storage_bucket": "fruits-hub-c571a.appspot.com"
  },
  "client": [
    {
      "client_info": {
        "mobilesdk_app_id": "1:1042387473888:android:ab13531919eb6c048e4785",
        "android_client_info": {
          "package_name": "com.example.app"
        }
      },
      "oauth_client": [],
      "api_key": [
        {
          "current_key": "AIzaSyBsShusLQ0hap-lhIhkXZ0ZFsey9p5PKlo"
        }
      ],
      "services": {
        "appinvite_service": {
          "other_platform_oauth_client": []
        }
      }
    },
    {
      "client_info": {
        "mobilesdk_app_id": "1:1042387473888:android:fec43fe53b6035758e4785",
        "android_client_info": {
          "package_name": "com.example.fruits_hub"
        }
      },
      "oauth_client": [],
      "api_key": [
        {
          "current_key": "AIzaSyBsShusLQ0hap-lhIhkXZ0ZFsey9p5PKlo"
        }
      ],
      "services": {
        "appinvite_service": {
          "other_platform_oauth_client": []
        }
      }
    }
  ],
  "configuration_version": "1"
}